milvus_fake_data-0.2.0.dist-info/METADATA
milvus_fake_data-0.2.0.dist-info/WHEEL
milvus_fake_data-0.2.0.dist-info/entry_points.txt
milvus_fake_data/__init__.py
milvus_fake_data/builtin_schemas.py
milvus_fake_data/cli.py
milvus_fake_data/exceptions.py
milvus_fake_data/generator.py
milvus_fake_data/logging_config.py
milvus_fake_data/models.py
milvus_fake_data/optimized_writer.py
milvus_fake_data/rich_display.py
milvus_fake_data/schema_manager.py
milvus_fake_data/schemas/__init__.py
milvus_fake_data/schemas/documents.json
milvus_fake_data/schemas/ecommerce.json
milvus_fake_data/schemas/images.json
milvus_fake_data/schemas/news.json
milvus_fake_data/schemas/simple.json
milvus_fake_data/schemas/users.json
milvus_fake_data/schemas/videos.json
milvus_fake_data-0.2.0.dist-info/RECORD
