Metadata-Version: 2.1
Name: milvus-fake-data
Version: 0.2.0
Summary: High-performance mock data generator for Milvus collections with vectorized operations
Keywords: milvus,vector-database,mock-data,fake-data,data-generation,high-performance,vectorization
Author-Email: zhuwenxing <wenxing.zhu@zilliz.com>
License: MIT
Classifier: Development Status :: 4 - Beta
Classifier: Intended Audience :: Developers
Classifier: License :: OSI Approved :: MIT License
Classifier: Programming Language :: Python :: 3
Classifier: Programming Language :: Python :: 3.10
Classifier: Programming Language :: Python :: 3.11
Classifier: Programming Language :: Python :: 3.12
Classifier: Topic :: Database
Classifier: Topic :: Software Development :: Testing
Classifier: Topic :: Scientific/Engineering
Classifier: Topic :: System :: Benchmark
Classifier: Operating System :: OS Independent
Requires-Python: >=3.10
Requires-Dist: faker>=23.0.0
Requires-Dist: numpy>=1.24.0
Requires-Dist: pandas>=2.0.0
Requires-Dist: pyarrow>=14.0.0
Requires-Dist: click>=8.0.0
Requires-Dist: pyyaml>=6.0.0
Requires-Dist: pymilvus[bulk_writer]
Requires-Dist: pydantic>=2.0.0
Requires-Dist: rich>=13.0.0
Requires-Dist: loguru>=0.7.3
